jhpce/jhpce-gui.py
jhpce/keygen.py
jhpce/module.py
jhpce-0.0.2.dist-info/METADATA
jhpce-0.0.2.dist-info/WHEEL
jhpce-0.0.2.dist-info/licenses/LICENSE
jhpce-0.0.2.dist-info/RECORD
