Metadata-Version: 2.3
Name: jhpce
Version: 0.0.2
Summary: A package for using python to work on the Johns Hopkins Joint High performance Computing Exchange
Project-URL: Homepage, https://github.com/jhpce-jhu/jhpce-python
Project-URL: Issues, https://github.com/jhpce-jhu/jhpce-python/issues
Author-email: Brian Caffo <bcaffo@gmail.com>
License-File: LICENSE
Classifier: License :: OSI Approved :: MIT License
Classifier: Operating System :: OS Independent
Classifier: Programming Language :: Python :: 3
Requires-Python: >=3.8
